glare/__init__.py
glare/engine.py
glare/i18n.py
glare/locking.py
glare/notification.py
glare/opts.py
glare/quota.py
glare/scrubber.py
glare/version.py
glare/wsgi.py
glare/api/__init__.py
glare/api/versions.py
glare/api/middleware/__init__.py
glare/api/middleware/context.py
glare/api/middleware/fault.py
glare/api/middleware/keycloak_auth.py
glare/api/middleware/version_negotiation.py
glare/api/v1/__init__.py
glare/api/v1/api_version_request.py
glare/api/v1/api_versioning.py
glare/api/v1/resource.py
glare/api/v1/router.py
glare/cmd/__init__.py
glare/cmd/api.py
glare/cmd/db_manage.py
glare/cmd/scrubber.py
glare/common/__init__.py
glare/common/config.py
glare/common/exception.py
glare/common/policy.py
glare/common/semver_db.py
glare/common/store_api.py
glare/common/utils.py
glare/common/wsgi.py
glare/db/__init__.py
glare/db/artifact_api.py
glare/db/migration/__init__.py
glare/db/migration/alembic.ini
glare/db/migration/migration.py
glare/db/migration/alembic_migrations/README
glare/db/migration/alembic_migrations/env.py
glare/db/migration/alembic_migrations/script.py.mako
glare/db/migration/alembic_migrations/versions/001_initial_version.py
glare/db/migration/alembic_migrations/versions/002_add_acquired_at_column.py
glare/db/migration/alembic_migrations/versions/003_add_database_blob_storage.py
glare/db/migration/alembic_migrations/versions/004_add_quota_tables.py
glare/db/migration/alembic_migrations/versions/005_added_display_name.py
glare/db/sqlalchemy/__init__.py
glare/db/sqlalchemy/api.py
glare/db/sqlalchemy/models.py
glare/hacking/__init__.py
glare/hacking/checks.py
glare/objects/__init__.py
glare/objects/all.py
glare/objects/base.py
glare/objects/heat_environment.py
glare/objects/heat_template.py
glare/objects/image.py
glare/objects/murano_package.py
glare/objects/secret.py
glare/objects/tosca_template.py
glare/objects/meta/__init__.py
glare/objects/meta/fields.py
glare/objects/meta/file_utils.py
glare/objects/meta/registry.py
glare/objects/meta/validators.py
glare-5.0.1.dist-info/AUTHORS
glare-5.0.1.dist-info/LICENSE
glare-5.0.1.dist-info/METADATA
glare-5.0.1.dist-info/WHEEL
glare-5.0.1.dist-info/entry_points.txt
glare-5.0.1.dist-info/pbr.json
glare-5.0.1.dist-info/top_level.txt
glare-5.0.1.dist-info/RECORD
