Metadata-Version: 2.1
Name: glare
Version: 5.0.1
Summary: OpenStack Artifact Service
Home-page: http://docs.openstack.org/developer/glare/
Author: OpenStack
Author-email: openstack-dev@lists.openstack.org
License: UNKNOWN
Platform: UNKNOWN
Classifier: Environment :: OpenStack
Classifier: Intended Audience :: Information Technology
Classifier: Intended Audience :: System Administrators
Classifier: License :: OSI Approved :: Apache Software License
Classifier: Operating System :: POSIX :: Linux
Classifier: Programming Language :: Python
Classifier: Programming Language :: Python :: 2
Classifier: Programming Language :: Python :: 2.7
Classifier: Programming Language :: Python :: 3
Classifier: Programming Language :: Python :: 3.5
Requires-Dist: pbr (!=2.1.0,>=2.0.0)
Requires-Dist: SQLAlchemy (!=1.1.5,!=1.1.6,!=1.1.7,!=1.1.8,>=1.0.10)
Requires-Dist: alembic (>=0.8.10)
Requires-Dist: eventlet (!=0.18.3,!=0.20.1,>=0.18.2)
Requires-Dist: PasteDeploy (>=1.5.0)
Requires-Dist: Routes (>=2.3.1)
Requires-Dist: WebOb (>=1.7.1)
Requires-Dist: httplib2 (>=0.9.1)
Requires-Dist: oslo.config (>=5.1.0)
Requires-Dist: oslo.concurrency (>=3.20.0)
Requires-Dist: oslo.context (>=2.19.2)
Requires-Dist: oslo.service (>=1.24.0)
Requires-Dist: oslo.utils (>=3.31.0)
Requires-Dist: futurist (>=1.2.0)
Requires-Dist: taskflow (>=2.7.0)
Requires-Dist: keystoneauth1 (>=3.3.0)
Requires-Dist: keystonemiddleware (>=4.17.0)
Requires-Dist: python-memcached (>=1.56)
Requires-Dist: WSME (>=0.8.0)
Requires-Dist: PyJWT (>=1.6.0)
Requires-Dist: cryptography (!=2.0,>=1.9)
Requires-Dist: Paste (>=2.0.2)
Requires-Dist: jsonpatch (>=1.16)
Requires-Dist: jsonschema (>=2.6.0)
Requires-Dist: pyOpenSSL (>=16.2.0)
Requires-Dist: six (>=1.10.0)
Requires-Dist: oslo.db (>=4.27.0)
Requires-Dist: oslo.i18n (>=3.15.3)
Requires-Dist: oslo.log (>=3.30.0)
Requires-Dist: oslo.messaging (>=5.29.0)
Requires-Dist: oslo.middleware (>=3.31.0)
Requires-Dist: oslo.policy (>=1.23.0)
Requires-Dist: oslo.serialization (!=2.19.1,>=2.18.0)
Requires-Dist: oslo.versionedobjects (>=1.28.0)
Requires-Dist: retrying (!=1.3.0,>=1.2.3)
Requires-Dist: osprofiler (>=1.4.0)
Requires-Dist: glance-store (>=0.22.0)
Requires-Dist: microversion-parse (>=0.1.2)
Requires-Dist: semantic-version (>=2.3.1)
Requires-Dist: iso8601 (>=0.1.11)
Requires-Dist: monotonic (>=0.6) ; (python_version<'3.3')
